[
  {
    "title": "Short Stories in Spanish for Beginners",
    "author": "Olly Richards",
    "price": "US$10.37US$14.99",
    "coverImg": "https://d1w7fb2mkkr3kw.cloudfront.net/assets/images/book/mid/9781/4736/9781473683259.jpg",
    "rating": 4
  },
  {
    "title": "Volver a empezar (It Starts with Us)",
    "author": "Colleen Hoover",
    "price": "US$30.94",
    "coverImg": "https://d1w7fb2mkkr3kw.cloudfront.net/assets/images/book/mid/9788/4082/9788408267195.jpg",
    "rating": 4
  },
  {
    "title": "Twisted 2 - Twisted Games",
    "author": "Ana Huang",
    "price": "US$17.16US$18.57",
    "coverImg": "https://d1w7fb2mkkr3kw.cloudfront.net/assets/images/book/mid/9788/4082/9788408267041.jpg",
    "rating": 0
  },
  {
    "title": "Elysian",
    "author": "Sugary Pale",
    "price": "US$17.82US$19.60",
    "coverImg": "https://d1w7fb2mkkr3kw.cloudfront.net/assets/images/book/mid/9788/4082/9788408267836.jpg",
    "rating": 0
  },
  {
    "title": "Cuando Las Mujeres Comen",
    "author": "Noelia Janet Previtera",
    "price": "US$13.52",
    "coverImg": "https://d1w7fb2mkkr3kw.cloudfront.net/assets/images/book/mid/9798/3613/9798361328277.jpg",
    "rating": 0
  },
  {
    "title": "El Arte De Ser Nosotros",
    "author": "Inma Rubiales",
    "price": "US$17.13US$18.51",
    "coverImg": "https://d1w7fb2mkkr3kw.cloudfront.net/assets/images/book/mid/9788/4082/9788408267928.jpg",
    "rating": 4.5
  },
  {
    "title": "El Reino Del Puente",
    "author": "Danielle L. Jensen",
    "price": "US$17.82US$19.60",
    "coverImg": "https://d1w7fb2mkkr3kw.cloudfront.net/assets/images/book/mid/9788/4082/9788408267027.jpg",
    "rating": 4
  },
  {
    "title": "Fortaleza. Agenda Paulo Coelho 2023",
    "author": "Paulo Coelho",
    "price": "US$23.59",
    "coverImg": "https://d1w7fb2mkkr3kw.cloudfront.net/assets/images/book/mid/9788/4082/9788408256854.jpg",
    "rating": 0
  },
  {
    "title": "En la sombra",
    "author": "Principe Harry",
    "price": "US$35.94",
    "coverImg": "https://d1w7fb2mkkr3kw.cloudfront.net/assets/images/book/mid/9788/4010/9788401029813.jpg",
    "rating": 3
  },
  {
    "title": "Short Stories in Spanish for Intermediate Learners",
    "author": "Olly Richards",
    "price": "US$10.20US$14.99",
    "coverImg": "https://d1w7fb2mkkr3kw.cloudfront.net/assets/images/book/mid/9781/5293/9781529361810.jpg",
    "rating": 4
  },
  {
    "title": "Spanish-English Bilingual Visual Dictionary with Free Audio App",
    "author": "DK",
    "price": "US$13.75",
    "coverImg": "https://d1w7fb2mkkr3kw.cloudfront.net/assets/images/book/mid/9780/2412/9780241292433.jpg",
    "rating": 4.5
  },
  {
    "title": "Campos de fresas",
    "author": "Jordi Sierra I Fabra",
    "price": "US$18.82US$30.30",
    "coverImg": "https://d1w7fb2mkkr3kw.cloudfront.net/assets/images/book/mid/9788/4675/9788467593945.jpg",
    "rating": 3.5
  },
  {
    "title": "(pack) Bad Ash (trilogia)",
    "author": "Alina Not",
    "price": "US$27.63US$30.87",
    "coverImg": "https://d1w7fb2mkkr3kw.cloudfront.net/assets/images/book/mid/9788/4082/9788408268543.jpg",
    "rating": 0
  },
  {
    "title": "Eximidos",
    "author": "Mar Petryk",
    "price": "US$34.08",
    "coverImg": "https://d1w7fb2mkkr3kw.cloudfront.net/assets/images/book/mid/9788/4082/9788408266990.jpg",
    "rating": 4.5
  },
  {
    "title": "Pack Orden y caos: 24 reglas para vivir",
    "author": "Jordan B. Peterson",
    "price": "US$32.42US$33.69",
    "coverImg": "https://d1w7fb2mkkr3kw.cloudfront.net/assets/images/book/mid/9788/4082/9788408256328.jpg",
    "rating": 0
  },
  {
    "title": "HABITOS ATOMICOS",
    "author": "CLEAR, JAMES",
    "price": "US$20.41",
    "coverImg": "https://d1w7fb2mkkr3kw.cloudfront.net/assets/images/book/mid/9786/0774/9786077476719.jpg",
    "rating": 4.5
  },
  {
    "title": "No me puedes lastimar",
    "author": "David Goggins",
    "price": "US$27.13",
    "coverImg": "https://d1w7fb2mkkr3kw.cloudfront.net/assets/images/book/mid/9781/5445/9781544529127.jpg",
    "rating": 4.5
  },
  {
    "title": "La liberaci칩n del alma : el viaje m치s all치 de ti mismo",
    "author": "Michael A. Singer",
    "price": "US$20.41",
    "coverImg": "https://d1w7fb2mkkr3kw.cloudfront.net/assets/images/book/mid/9788/4844/9788484455110.jpg",
    "rating": 4
  },
  {
    "title": "Colega",
    "author": "Elena G. Gonz치lez",
    "price": "US$36.15US$180.77",
    "coverImg": "https://d1w7fb2mkkr3kw.cloudfront.net/assets/images/book/mid/9788/4771/9788477116721.jpg",
    "rating": 1
  },
  {
    "title": "Maneras de Amar -V2*",
    "author": "Rachel Heller",
    "price": "US$16.25",
    "coverImg": "https://d1w7fb2mkkr3kw.cloudfront.net/assets/images/book/mid/9788/4158/9788415870869.jpg",
    "rating": 4
  }
]